s3import-0.6.4.dist-info/top_level.txt
s3import-0.6.4.dist-info/entry_points.txt
s3import-0.6.4.dist-info/RECORD
s3import-0.6.4.dist-info/METADATA
s3import-0.6.4.dist-info/DESCRIPTION.rst
s3import-0.6.4.dist-info/WHEEL
s3import-0.6.4.dist-info/metadata.json
s3import/exceptions.py
s3import/_patches.py
s3import/cli.py
s3import/importer.py
s3import/contexts.py
s3import/__init__.py
s3import/tools/size.py
s3import/tools/__init__.py
s3import/tools/converters.py
s3import/tools/string_helpers.py
s3import/stream/__init__.py
s3import/stream/downloaded.py
s3import/stream/chunked.py
