Metadata-Version: 2.0
Name: s3import
Version: 0.6.4
Summary: S3 data import utility
Home-page: http://www.skylable.com/products
Author: Skylable Ltd.
Author-email: sx-users@lists.skylable.com
License: Apache 2.0
Platform: UNKNOWN
Classifier: Development Status :: 4 - Beta
Classifier: Intended Audience :: System Administrators
Classifier: Intended Audience :: Developers
Classifier: Natural Language :: English
Classifier: License :: OSI Approved :: Apache Software License
Classifier: Programming Language :: Python
Classifier: Programming Language :: Python :: 2.7
Requires-Dist: boto (==2.39.0)
Requires-Dist: sxclient (>=0.16.4)
